demo/manage.py
demo/theapp/__init__.py
demo/theapp/admin.py
demo/theapp/apps.py
demo/theapp/models.py
demo/theapp/tests.py
demo/theapp/urls.py
demo/theapp/views.py
demo/theapp/migrations/__init__.py
demo/theproject/__init__.py
demo/theproject/asgi.py
demo/theproject/settings.py
demo/theproject/urls.py
demo/theproject/wsgi.py
svgicon/__init__.py
svgicon/apps.py
svgicon/constants.py
svgicon/helpers.py
svgicon/middleware.py
svgicon/settings.py
svgicon/tracker.py
svgicon/templatetags/__init__.py
svgicon/templatetags/svgicon.py
django_svgicon-0.1.2.dist-info/METADATA
django_svgicon-0.1.2.dist-info/WHEEL
django_svgicon-0.1.2.dist-info/top_level.txt
django_svgicon-0.1.2.dist-info/RECORD
