Metadata-Version: 2.2
Name: django-svgicon
Version: 0.1.2
Summary: SVG icons for Django.
Author: MeyT
License: MIT
Project-URL: Documentation, https://github.com/meyt/django-svgicon
Project-URL: Source, https://github.com/meyt/django-svgicon
Project-URL: Tracker, https://github.com/meyt/django-svgicon/issues
Classifier: Development Status :: 4 - Beta
Classifier: Intended Audience :: Developers
Classifier: License :: OSI Approved :: MIT License
Classifier: Programming Language :: Python :: 3
Classifier: Programming Language :: Python :: 3.10
Classifier: Programming Language :: Python :: 3.11
Classifier: Programming Language :: Python :: 3.12
Classifier: Programming Language :: Python :: 3.13
Classifier: Framework :: Django
Classifier: Framework :: Django :: 5
Classifier: Topic :: Software Development :: Libraries :: Python Modules
Classifier: Topic :: Internet :: WWW/HTTP
Classifier: Topic :: Internet :: WWW/HTTP :: Dynamic Content
Classifier: Operating System :: OS Independent
Classifier: Environment :: Web Environment
Requires-Python: >=3.10
Requires-Dist: django>=5
Provides-Extra: lxml
Requires-Dist: lxml; extra == "lxml"
